{
  "documentation": "\"This file is a QMK Configurator export. You can import this at <https://config.qmk.fm>. It can also be used directly with QMK's source code.\n\nTo setup your QMK environment check out the tutorial: <https://docs.qmk.fm/#/newbs>\n\nYou can convert this file to a keymap.c using this command: `qmk json2c {keymap}`\n\nYou can compile this keymap using this command: `qmk compile {keymap}`\"\n",
  "notes": "",
  "version": 1,
  "keyboard": "adafruit/pico_pad",
  "keymap": "adafruit_pico_pad_layout_2026-06-09",
  "layout": "LAYOUT",
  "layers": [
    [
      "KC_PSCR",
      "KC_UNDO",
      "KC_PWR",
      "KC_NO",
      "KC_NO",
      "KC_NO",
      "KC_NO",
      "KC_FIND",
      "KC_COPY",
      "KC_MRWD",
      "KC_NO",
      "KC_NO",
      "KC_NO",
      "KC_NO",
      "TG(1)",
      "KC_PSTE",
      "KC_MPLY",
      "KC_NO",
      "KC_NO",
      "KC_NO",
      "KC_NO"
    ],
    [
      "KC_DEL",
      "KC_END",
      "KC_SCRL",
      "KC_NO",
      "KC_NO",
      "KC_NO",
      "KC_NO",
      "KC_PGUP",
      "KC_PGDN",
      "KC_LCTL",
      "KC_NO",
      "KC_NO",
      "KC_NO",
      "KC_NO",
      "TG(0)",
      "KC_TAB",
      "KC_LALT",
      "KC_NO",
      "KC_NO",
      "KC_NO",
      "KC_NO"
    ]
  ],
  "author": ""
}